PTMCMCSampler/PTMCMCSampler.py
PTMCMCSampler/__init__.py
PTMCMCSampler/nompi4py.py
PTMCMCSampler/nutsjump.py
PTMCMCSampler/version.py
ptmcmcsampler-2.1.4.dist-info/licenses/LICENSE
ptmcmcsampler-2.1.4.dist-info/METADATA
ptmcmcsampler-2.1.4.dist-info/WHEEL
ptmcmcsampler-2.1.4.dist-info/top_level.txt
ptmcmcsampler-2.1.4.dist-info/RECORD
