Metadata-Version: 2.4
Name: ptmcmcsampler
Version: 2.1.4
Summary: Parallel tempering MCMC sampler written in Python
Home-page: https://github.com/nanograv/PTMCMCSampler
Author: Justin A. Ellis, Rutger van Haasteren
Author-email: rutger@vhaasteren.com
Maintainer: Aaron D. Johnson, Paul T. Baker, Ken D. Olum
License: MIT
Classifier: Development Status :: 5 - Production/Stable
Classifier: Intended Audience :: Developers
Classifier: Intended Audience :: Science/Research
Classifier: License :: OSI Approved :: MIT License
Classifier: Operating System :: OS Independent
Classifier: Programming Language :: Python :: 3
Classifier: Programming Language :: Python :: 3.8
Classifier: Programming Language :: Python :: 3.9
Classifier: Programming Language :: Python :: 3.10
Classifier: Programming Language :: Python :: 3.11
Requires-Python: >=3.8
License-File: LICENSE
Requires-Dist: numpy>=1.16.3
Requires-Dist: scipy>=1.2.0
Provides-Extra: mpi
Requires-Dist: mpi4py>=3.0.3; extra == "mpi"
Dynamic: author
Dynamic: author-email
Dynamic: classifier
Dynamic: description
Dynamic: description-content-type
Dynamic: home-page
Dynamic: license
Dynamic: license-file
Dynamic: maintainer
Dynamic: provides-extra
Dynamic: requires-dist
Dynamic: requires-python
Dynamic: summary
